{
  "titre": "Fièvre 1",
  "description": "M. Pierre Robin, 26 ans, coiffeur, consulte pour fièvre élevée depuis 5 jours.",
  "signesVitaux": {
    "tensionArterielle": "105/75 mmHg",
    "frequenceCardiaque": "95 bpm",
    "frequenceRespiratoire": "19/min",
    "temperature": "39.1°C",
    "sao2": "94 %"
  },
  "taches": [
    "Effectuer une anamnèse ciblée sur la fièvre et rechercher les facteurs de risque",
    "Réaliser un examen clinique cardio-vasculaire et pulmonaire complet",
    "Rechercher des signes méningés et inspecter la cavité buccale",
    "Évoquer un diagnostic différentiel cohérent (endocardite, pneumonie, méningite)",
    "Proposer des examens paracliniques appropriés (hémocultures, radiographie thorax, ECG)"
  ],
  "contexte": "Urgences"
}