{
  "titre": "USMLE Triage 37 - Cas téléphonique - Chute d'une personne âgée",
  "contexte": "Consultation téléphonique - Cabinet médical",
  "description": "Marilyn O'Neal appelle concernant sa mère Lori (86 ans) après chute dans les escaliers.",
  "remarque": "Consultation par téléphone via la fille (patiente démente) - Aucun examen physique possible",
  "taches": [
    "Obtenir une anamnèse ciblée",
    "Ne pas effectuer d'examen physique",
    "Discuter de votre impression diagnostique initiale et de votre plan de prise en charge"
  ]
}