{
  "title": "Céphalées I",
  "context": {
    "setting": "Cabinet de médecine générale",
    "patient": "Homme de 70 ans consultant pour contrôle de tension artérielle, mentionne des céphalées"
  },
  "sections": {
    "anamnese": {
      "weight": 0.4,
      "criteria": [
        {
          "id": "a1",
          "text": "Présentation avec nom, fonction, objectif",
          "binaryOnly": true
        },
        {
          "id": "a2",
          "text": "Question ouverte d'introduction → Symptôme principal",
          "patientComment": "Céphalées",
          "binaryOnly": true
        },
        {
          "id": "a3",
          "text": "Localisation des douleurs : unilatérale/bilatérale, tête ou visage",
          "patientComment": "Plus à gauche qu'à droite, pas dans le visage"
        },
        {
          "id": "a4",
          "text": "Début de la douleur, durée, constante/intermittente",
          "patientComment": "Depuis ce matin"
        },
        {
          "id": "a5",
          "text": "Variation dans la journée : matin vs soir",
          "patientComment": "Pire le matin, depuis ce matin seulement"
        },
        {
          "id": "a6",
          "text": "Intensité de la douleur",
          "patientComment": "5/10"
        },
        {
          "id": "a7",
          "text": "Caractère de la douleur",
          "patientComment": "Sourde"
        },
        {
          "id": "a8",
          "text": "Irradiation",
          "patientComment": "Difficile à dire, pas vraiment"
        },
        {
          "id": "a9",
          "text": "Facteurs de soulagement",
          "patientComment": "Dormir"
        },
        {
          "id": "a10",
          "text": "Facteurs aggravants",
          "patientComment": "Aucun"
        },
        {
          "id": "a11",
          "text": "Symptômes d'accompagnement : nausées, vomissements, photophobie, larmoiement, douleurs à la mastication, troubles visuels",
          "patientComment": "Non"
        },
        {
          "id": "a12",
          "text": "Première fois ou connu",
          "patientComment": "Habituellement peu de céphalées, mais pas complètement inconnu"
        },
        {
          "id": "a13",
          "text": "Maladies récentes",
          "patientComment": "Aucune"
        },
        {
          "id": "a14",
          "text": "Fièvre",
          "patientComment": "Pas de fièvre, mais avant-hier ne se sentait pas bien, peut-être"
        },
        {
          "id": "a15",
          "text": "Raideur de nuque",
          "patientComment": "Non"
        },
        {
          "id": "a16",
          "text": "Traumatisme",
          "patientComment": "Non"
        },
        {
          "id": "a17",
          "text": "Crises convulsives",
          "patientComment": "Qu'est-ce que c'est ?"
        },
        {
          "id": "a18",
          "text": "Douleurs aux épaules et muscles",
          "patientComment": "Oui depuis environ une semaine, peut-être du bodypump"
        },
        {
          "id": "a19",
          "text": "Stress, consommation de caféine",
          "patientComment": "Pas de stress, 4-5 cafés par jour, mais pas encore aujourd'hui"
        },
        {
          "id": "a20",
          "text": "Alimentation",
          "patientComment": "Hier au restaurant chinois, fête d'anniversaire copieuse"
        },
        {
          "id": "a21",
          "text": "Piqûre de tique",
          "patientComment": "Ne se souvient pas"
        },
        {
          "id": "a22",
          "text": "Antécédents personnels",
          "patientComment": "Hypertension artérielle, pas de néoplasie"
        },
        {
          "id": "a23",
          "text": "Médicaments",
          "patientComment": "Coversum-Combi, pas d'antalgiques"
        },
        {
          "id": "a24",
          "text": "Contraceptifs oraux (chez la femme)",
          "patientComment": "Non applicable"
        },
        {
          "id": "a25",
          "text": "Toxiques",
          "patientComment": "Aucun, rarement alcool, hier un peu plus évidemment"
        },
        {
          "id": "a26",
          "text": "Allergies",
          "patientComment": "Pénicilline"
        },
        {
          "id": "a27",
          "text": "Antécédents familiaux",
          "patientComment": "Pas de migraine, père décédé d'AVC"
        },
        {
          "id": "a28",
          "text": "Anamnèse sociale, profession",
          "patientComment": "Contrôleur SBB retraité, marié"
        },
        {
          "id": "a29",
          "text": "Évaluation globale de la qualité de l'anamnèse",
          "binaryOnly": false,
          "details": [
            "Anamnèse générale ciblée et bien conduite"
          ],
          "scoringRule": "Bien = oui, suffisant = ±, insuffisant = non"
        }
      ]
    },
    "examen": {
      "weight": 0.3,
      "criteria": [
        {
          "id": "e1",
          "text": "Signes vitaux",
          "patientComment": "TA 160/100, sinon normal"
        },
        {
          "id": "e2",
          "text": "Recherche de méningisme",
          "patientComment": "Négatif"
        },
        {
          "id": "e3",
          "text": "Status neurologique",
          "patientComment": "Normal"
        },
        {
          "id": "e4",
          "text": "Examen des pupilles, fond d'œil",
          "patientComment": "À examiner"
        },
        {
          "id": "e5",
          "text": "Palpation de l'artère temporale",
          "patientComment": "À examiner"
        },
        {
          "id": "e6",
          "text": "Auscultation cardiaque avec artères carotides",
          "patientComment": "À examiner"
        },
        {
          "id": "e7",
          "text": "Évaluation globale de la qualité de l'examen clinique",
          "binaryOnly": false,
          "details": [
            "Status général ciblé et bien conduit"
          ],
          "scoringRule": "Bien = oui, suffisant = ±, insuffisant = non"
        }
      ]
    },
    "management": {
      "weight": 0.2,
      "criteria": [
        {
          "id": "m1",
          "text": "L'étudiant évoque le diagnostic principal : Céphalée du restaurant chinois (Chinese-Restaurant-Headache)"
        },
        {
          "id": "m2",
          "text": "L'étudiant évoque au moins 2 diagnostics différentiels",
          "details": [
            "Céphalée de tension (gueule de bois) de l'alcool d'hier",
            "Sevrage caféinique",
            "Déshydratation",
            "Maladie de Horton"
          ]
        },
        {
          "id": "m3",
          "text": "L'étudiant évoque les étapes diagnostiques appropriées",
          "details": [
            "BSR (vitesse de sédimentation)",
            "Numération formule sanguine",
            "Scanner cérébral (CT) si nécessaire"
          ]
        },
        {
          "id": "m4",
          "text": "L'étudiant évoque les possibilités thérapeutiques appropriées",
          "details": [
            "En cas de maladie de Horton : cortisone et référence spécialisée",
            "Sinon : antalgiques et contrôle de suivi"
          ]
        },
        {
          "id": "m5",
          "text": "Évaluation globale de la qualité de la prise en charge",
          "binaryOnly": false,
          "details": [
            "Prise en charge générale cohérente et bien conduite"
          ],
          "scoringRule": "Bien = oui, suffisant = ±, insuffisant = non"
        }
      ]
    },
    "communication": {
      "weight": 0.1,
      "criteria": [
        {
          "id": "c1",
          "text": "Communication globale appropriée",
          "patientComment": "Évaluation globale compétent/non compétent"
        }
      ]
    }
  }
}